orcabridge/__init__.py
orcabridge-0.0.1.dist-info/METADATA
orcabridge-0.0.1.dist-info/WHEEL
orcabridge-0.0.1.dist-info/top_level.txt
orcabridge-0.0.1.dist-info/RECORD
